README.md
setup.py
src/PythonFreePoint/__init__.py
src/PythonFreePoint/main.py
src/PythonFreePoint.egg-info/PKG-INFO
src/PythonFreePoint.egg-info/SOURCES.txt
src/PythonFreePoint.egg-info/dependency_links.txt
src/PythonFreePoint.egg-info/top_level.txt