Metadata-Version: 2.1
Name: PythonFreePoint
Version: 0.0.0a3
Summary: Free Point Style for Python
Home-page: https://github.com/itruffat/python_point_free
Author: itrufat
Classifier: Development Status :: 3 - Alpha
Classifier: Intended Audience :: Developers
Classifier: License :: OSI Approved :: MIT License
Classifier: Programming Language :: Python :: 3
Classifier: Programming Language :: Python :: 3.6
Classifier: Programming Language :: Python :: 3.7
Classifier: Programming Language :: Python :: 3.8
Classifier: Programming Language :: Python :: 3.9
